Metadata-Version: 2.1
Name: classification-model
Version: 0.0.1
Summary: Classification model for animal activity recognition based on XGBoost
Author: Rihab Feki
Author-email: rihabfeki8@gmail.com
License: BSD 2
Platform: UNKNOWN
Classifier: License :: OSI Approved :: MIT License
Classifier: Programming Language :: Python
Classifier: Programming Language :: Python :: 3
Classifier: Programming Language :: Python :: 3.9
Classifier: Programming Language :: Python :: 3.10
Classifier: Programming Language :: Python :: 3.11
Classifier: Programming Language :: Python :: Implementation :: CPython
Classifier: Programming Language :: Python :: Implementation :: PyPy
Requires-Python: >=3.9.5
Requires-Dist: numpy (<1.23.0,>=1.22.2)
Requires-Dist: pandas (<1.3.0,>=1.2.2)
Requires-Dist: pydantic (<1.9.0,>=1.8.2)
Requires-Dist: scikit-learn (<0.25.0,>=0.24.2)
Requires-Dist: strictyaml (<1.7.0,>=1.6.1)
Requires-Dist: joblib (<1.1.0,>=1.0.1)
Requires-Dist: xgboost (<1.6.0,>=1.5.2)
Requires-Dist: pytest (<7.1.0,>=7.0.1)
Requires-Dist: setuptools (<56.1.0,>=56.0.0)
Requires-Dist: wheel (<0.37.0,>=0.36.2)
